Metadata-Version: 2.1
Name: xkbregistry
Version: 1.0
Summary: Bindings for libxkbregistry using cffi
Home-page: https://github.com/sde1000/python-xkbregistry
Author: Stephen Early
Author-email: steve@assorted.org.uk
License: MIT
Classifier: Development Status :: 4 - Beta
Classifier: License :: OSI Approved :: MIT License
Classifier: Programming Language :: Python :: 3.8
Classifier: Programming Language :: Python :: 3.9
Classifier: Programming Language :: Python :: 3.10
Classifier: Programming Language :: Python :: 3.11
Classifier: Programming Language :: Python :: 3.12
Classifier: Topic :: Software Development :: Libraries
Classifier: Intended Audience :: Developers
Requires-Python: >=3.8
License-File: LICENSE
